agent_team_chat/__init__.py
agent_team_chat/database.py
agent_team_chat/docs.py
agent_team_chat/events.py
agent_team_chat/frontend.py
agent_team_chat/rate_limiter.py
agent_team_chat/server.py
agent_team_chat/tools.py
agent_team_chat/utils.py
agent_team_chat/frontend_files/api-client.js
agent_team_chat/frontend_files/index.html
agent_team_chat_enhanced-0.1.0.dist-info/METADATA
agent_team_chat_enhanced-0.1.0.dist-info/WHEEL
agent_team_chat_enhanced-0.1.0.dist-info/entry_points.txt
agent_team_chat_enhanced-0.1.0.dist-info/top_level.txt
agent_team_chat_enhanced-0.1.0.dist-info/RECORD
