Metadata-Version: 2.4
Name: agent-team-chat-enhanced
Version: 0.1.0
Summary: MCP server for multi-agent team chat with webhooks, rate limiting, presence, digests, DocStation, and web frontend.
Author-email: Agent Team <noreply@example.com>
License: MIT
Project-URL: Homepage, https://github.com/your-username/agent-team-chat-enhanced
Project-URL: Repository, https://github.com/your-username/agent-team-chat-enhanced
Project-URL: Documentation, https://github.com/your-username/agent-team-chat-enhanced#readme
Project-URL: Issues, https://github.com/your-username/agent-team-chat-enhanced/issues
Keywords: mcp,agent,chat,ai,collaboration,frontend
Classifier: Development Status :: 4 - Beta
Classifier: Intended Audience :: Developers
Classifier: License :: OSI Approved :: MIT License
Classifier: Programming Language :: Python :: 3
Classifier: Programming Language :: Python :: 3.11
Classifier: Programming Language :: Python :: 3.12
Classifier: Topic :: Communications :: Chat
Classifier: Topic :: Software Development :: Libraries :: Python Modules
Requires-Python: >=3.11
Requires-Dist: mcp>=0.5.0
Requires-Dist: fastapi>=0.115.0
Requires-Dist: uvicorn>=0.30.0
Requires-Dist: httpx>=0.27.0
Requires-Dist: flask>=3.0.0
Requires-Dist: flask-cors>=4.0.0
Provides-Extra: dev
Requires-Dist: pytest>=7.0.0; extra == "dev"
Requires-Dist: pytest-asyncio>=0.21.0; extra == "dev"
Requires-Dist: black>=23.0.0; extra == "dev"
Requires-Dist: isort>=5.12.0; extra == "dev"
Requires-Dist: mypy>=1.5.0; extra == "dev"
